MONSDA/Configurator.py
MONSDA/Deprecated.py
MONSDA/Logger.py
MONSDA/Params.py
MONSDA/RunMONSDA.py
MONSDA/Utils.py
MONSDA/Workflows.py
MONSDA/__init__.py
MONSDA/__main__.py
MONSDA/_version.py
MONSDA/lib/Collection.groovy
MONSDA-1.2.8.data/data/LICENSE
MONSDA-1.2.8.data/data/share/MONSDA/configs/template.json
MONSDA-1.2.8.data/data/share/MONSDA/configs/template_base_commented.json
MONSDA-1.2.8.data/data/share/MONSDA/configs/template_clean.json
MONSDA-1.2.8.data/data/share/MONSDA/configs/tutorial_exhaustive.json
MONSDA-1.2.8.data/data/share/MONSDA/configs/tutorial_postprocess.json
MONSDA-1.2.8.data/data/share/MONSDA/configs/tutorial_quick.json
MONSDA-1.2.8.data/data/share/MONSDA/configs/tutorial_toolmix.json
MONSDA-1.2.8.data/data/share/MONSDA/envs/LoveSonesonPatro.yaml
MONSDA-1.2.8.data/data/share/MONSDA/envs/base.yaml
MONSDA-1.2.8.data/data/share/MONSDA/envs/bbduk.yaml
MONSDA-1.2.8.data/data/share/MONSDA/envs/bbmap.yaml
MONSDA-1.2.8.data/data/share/MONSDA/envs/bedtools.yaml
MONSDA-1.2.8.data/data/share/MONSDA/envs/bwa.yaml
MONSDA-1.2.8.data/data/share/MONSDA/envs/bwa2.yaml
MONSDA-1.2.8.data/data/share/MONSDA/envs/bwameth.yaml
MONSDA-1.2.8.data/data/share/MONSDA/envs/ciri2.yaml
MONSDA-1.2.8.data/data/share/MONSDA/envs/countreads.yaml
MONSDA-1.2.8.data/data/share/MONSDA/envs/countreads_de.yaml
MONSDA-1.2.8.data/data/share/MONSDA/envs/cutadapt.yaml
MONSDA-1.2.8.data/data/share/MONSDA/envs/deseq2_DE.yaml
MONSDA-1.2.8.data/data/share/MONSDA/envs/dexseq_DEU.yaml
MONSDA-1.2.8.data/data/share/MONSDA/envs/dexseq_DTU.yaml
MONSDA-1.2.8.data/data/share/MONSDA/envs/diego_DAS.yaml
MONSDA-1.2.8.data/data/share/MONSDA/envs/dorado.yaml
MONSDA-1.2.8.data/data/share/MONSDA/envs/drimseq_DTU.yaml
MONSDA-1.2.8.data/data/share/MONSDA/envs/edger_DAS.yaml
MONSDA-1.2.8.data/data/share/MONSDA/envs/edger_DE.yaml
MONSDA-1.2.8.data/data/share/MONSDA/envs/edger_DEU.yaml
MONSDA-1.2.8.data/data/share/MONSDA/envs/fastp.yaml
MONSDA-1.2.8.data/data/share/MONSDA/envs/fastqc.yaml
MONSDA-1.2.8.dist-info/LICENSE
MONSDA-1.2.8.dist-info/METADATA
MONSDA-1.2.8.dist-info/WHEEL
MONSDA-1.2.8.dist-info/entry_points.txt
MONSDA-1.2.8.dist-info/top_level.txt
MONSDA-1.2.8.dist-info/RECORD
