Metadata-Version: 2.1
Name: MONSDA
Version: 1.2.8
Summary: MONSDA, Modular Organizer of Nextflow and Snakemake driven hts Data Analysis
Home-page: https://github.com/jfallmann/MONSDA
Author: Joerg Fallmann
Author-email: Joerg Fallmann <fallmann.joerg@gmail.com>
Maintainer-email: Joerg Fallmann <fallmann.joerg@gmail.com>
License: GNU GENERAL PUBLIC LICENSE
Project-URL: Homepage, https://github.com/jfallmann/MONSDA
Project-URL: Documentation, https://monsda.readthedocs.io/en/latest
Project-URL: Repository, https://github.com/jfallmann/MONSDA
Project-URL: Issues, https://github.com/jfallmann/MONSDA/issues
Requires-Python: >=3.12.0
License-File: LICENSE
Requires-Dist: biopython >=1.83
Requires-Dist: snakemake >=8.16.0
Requires-Dist: black >=21.5b2
Requires-Dist: flake8 >=3.8.3
Requires-Dist: isort >=5.13.2
Requires-Dist: sphinx >=4.1.0
